setup.py
miniimagenettools/__init__.py
miniimagenettools/mini_imagenet_dataloader.py
miniimagenettools/mini_imagenet_generator.py
miniimagenettools.egg-info/PKG-INFO
miniimagenettools.egg-info/SOURCES.txt
miniimagenettools.egg-info/dependency_links.txt
miniimagenettools.egg-info/requires.txt
miniimagenettools.egg-info/top_level.txt