Metadata-Version: 1.0
Name: miniimagenettools
Version: 0.2.2
Summary: Tools for generating mini-ImageNet dataset and processing batches
Home-page: https://mtl.yyliu.net
Author: yaoyaoliu
Author-email: yaoyaoliu@outlook.com
License: UNKNOWN
Platform: UNKNOWN
